ipypy/__init__.py
ipypy/config.py
ipypy/full.py
ipypy/ipyout.py
ipypy/ipypy.py
ipypy-0.1.2.dist-info/METADATA
ipypy-0.1.2.dist-info/WHEEL
ipypy-0.1.2.dist-info/top_level.txt
ipypy-0.1.2.dist-info/RECORD
