Metadata-Version: 2.1
Name: ipypy
Version: 0.1.2
Summary: ipypy notebook format
Home-page: UNKNOWN
License: UNKNOWN
Platform: UNKNOWN
